valency_anndata/__init__.py
valency_anndata/debug_utils.py
valency_anndata/py.typed
valency_anndata/scanpy.py
valency_anndata/utils.py
valency_anndata/datasets/__init__.py
valency_anndata/datasets/_load_aufstehen.py
valency_anndata/datasets/_load_chile_protest.py
valency_anndata/datasets/polis.py
valency_anndata/nbconvert/preprocessors.py
valency_anndata/preprocessing/__init__.py
valency_anndata/preprocessing/_impute.py
valency_anndata/preprocessing/_qc.py
valency_anndata/preprocessing/_rebuild_vote_matrix.py
valency_anndata/tools/__init__.py
valency_anndata/tools/_kmeans.py
valency_anndata/tools/_pacmap.py
valency_anndata/tools/_polis.py
valency_anndata/viz/__init__.py
valency_anndata/viz/_jupyter_scatter.py
valency_anndata/viz/_langevitour.py
valency_anndata/viz/_voter_vignette.py
valency_anndata/viz/schematic_diagram/__init__.py
valency_anndata/viz/schematic_diagram/_browser.py
valency_anndata/viz/schematic_diagram/_context.py
valency_anndata/viz/schematic_diagram/_schematic.py
valency_anndata/viz/schematic_diagram/_svg_blocks.py
valency_anndata/viz/schematic_diagram/_utils.py
valency_anndata-0.1.1.dist-info/METADATA
valency_anndata-0.1.1.dist-info/WHEEL
valency_anndata-0.1.1.dist-info/RECORD
