Metadata-Version: 2.4
Name: valency-anndata
Version: 0.1.1
Summary: Experimental tooling to support notebook analysis of polislike data
Project-URL: Homepage, https://github.com/patcon/valency-anndata
Project-URL: Documentation, https://github.com/patcon/valency-anndata#readme
Project-URL: Repository, https://github.com/patcon/valency-anndata
Project-URL: Bug Tracker, https://github.com/patcon/valency-anndata/issues
Project-URL: Changelog, https://github.com/patcon/valency-anndata/releases
Author-email: Patrick Connolly <patrick.c.connolly@gmail.com>
Keywords: anndata,clustering,data-analysis,dimensionality-reduction,opinion-data,polis,single-cell
Classifier: Development Status :: 3 - Alpha
Classifier: Intended Audience :: Developers
Classifier: Intended Audience :: Science/Research
Classifier: Operating System :: OS Independent
Classifier: Programming Language :: Python :: 3
Classifier: Programming Language :: Python :: 3.10
Classifier: Programming Language :: Python :: 3.11
Classifier: Programming Language :: Python :: 3.12
Classifier: Topic :: Scientific/Engineering :: Information Analysis
Classifier: Topic :: Scientific/Engineering :: Visualization
Requires-Python: >=3.10
Requires-Dist: anndata>=0.11.4
Requires-Dist: googletrans>=4.0.2
Requires-Dist: huggingface-hub
Requires-Dist: ipywidgets<8
Requires-Dist: jupyter-scatter>=0.22.2
Requires-Dist: langevitour>=0.8.0
Requires-Dist: llvmlite<=0.45.1; platform_system == 'Darwin' and platform_machine == 'x86_64'
Requires-Dist: nest-asyncio>=1.6.0
Requires-Dist: pacmap>=0.8.0
Requires-Dist: polis-client>=0.1.2
Requires-Dist: red-dwarf~=0.4.0
Requires-Dist: scanpy[leiden]
Requires-Dist: setuptools<81
Requires-Dist: svgwrite>=1.4.3
Provides-Extra: dev
Requires-Dist: ipykernel>=7.1.0; extra == 'dev'
Requires-Dist: itables>=2.6.2; extra == 'dev'
Requires-Dist: mkdocs-material[imaging]>=9.7.1; extra == 'dev'
Requires-Dist: mkdocs>=1.6.1; extra == 'dev'
Requires-Dist: mkdocstrings-python>=2.0.1; extra == 'dev'
Requires-Dist: nbconvert>=7.16.6; extra == 'dev'
Requires-Dist: ruff>=0.14.10; extra == 'dev'
